{
    "children": [
        {
            "children": [
                {
                    "children": [], 
                    "comp_anims": [], 
                    "event_list": [], 
                    "image": 101231, 
                    "name": "image_24", 
                    "pos": {
                        "__tuple__": true, 
                        "items": [
                            50.0, 
                            50.0
                        ]
                    }, 
                    "size": {
                        "__tuple__": true, 
                        "items": [
                            100.0, 
                            100.0
                        ]
                    }, 
                    "type": 4, 
                    "uid": "b757181e-196a-4894-a2cc-a81cb9c899b2"
                }, 
                {
                    "children": [], 
                    "comp_anims": [], 
                    "event_list": [], 
                    "image": 100070, 
                    "name": "image_25", 
                    "pos": {
                        "__tuple__": true, 
                        "items": [
                            51.0, 
                            50.0
                        ]
                    }, 
                    "pos_percent": {
                        "__tuple__": true, 
                        "items": [
                            51.0, 
                            50.0
                        ]
                    }, 
                    "size": {
                        "__tuple__": true, 
                        "items": [
                            100.0, 
                            100.0
                        ]
                    }, 
                    "type": 4, 
                    "uid": "6cf27b84-f6eb-4991-8cc8-a3b0dfc56b54"
                }, 
                {
                    "adapter_option": [
                        false, 
                        false, 
                        false, 
                        false, 
                        -11.633125305175781, 
                        16.36687469482422, 
                        -10.0, 
                        10.0
                    ], 
                    "bg_color": {
                        "__tuple__": true, 
                        "items": [
                            255, 
                            255, 
                            255, 
                            0
                        ]
                    }, 
                    "bg_image": 999, 
                    "children": [], 
                    "comp_anims": [], 
                    "event_list": [], 
                    "image": 100062, 
                    "name": "progress_9", 
                    "pos": {
                        "__tuple__": true, 
                        "items": [
                            50.0, 
                            50.0
                        ]
                    }, 
                    "progress_type": 0, 
                    "size": {
                        "__tuple__": true, 
                        "items": [
                            134.0, 
                            80.0
                        ]
                    }, 
                    "type": 5, 
                    "uid": "9237ae2c-c137-47c7-b559-47aab4954152"
                }, 
                {
                    "alignment": {
                        "__tuple__": true, 
                        "items": [
                            2, 
                            8
                        ]
                    }, 
                    "bold": true, 
                    "children": [], 
                    "comp_anims": [], 
                    "event_list": [], 
                    "label_effect": {
                        "__tuple__": true, 
                        "items": [
                            true, 
                            false, 
                            false, 
                            false
                        ]
                    }, 
                    "name": "label_1", 
                    "pos": {
                        "__tuple__": true, 
                        "items": [
                            50.0, 
                            50.0
                        ]
                    }, 
                    "text": {
                        "__tuple__": true, 
                        "items": [
                            "10", 
                            false
                        ]
                    }, 
                    "type": 3, 
                    "uid": "d3dabf1e-db2c-46d1-b1e4-819d3a2f2500"
                }, 
                {
                    "children": [], 
                    "comp_anims": [], 
                    "event_list": [], 
                    "font": {
                        "__tuple__": true, 
                        "items": [
                            "", 
                            24
                        ]
                    }, 
                    "name": "label_24", 
                    "pos": {
                        "__tuple__": true, 
                        "items": [
                            50.0, 
                            -12.0
                        ]
                    }, 
                    "pos_percent": {
                        "__tuple__": true, 
                        "items": [
                            50.0, 
                            -12.0
                        ]
                    }, 
                    "size": {
                        "__tuple__": true, 
                        "items": [
                            157.5999755859375, 
                            24.0
                        ]
                    }, 
                    "text": {
                        "__tuple__": true, 
                        "items": [
                            "lv.1 \u6069\u8d50\u89e3\u8131", 
                            false
                        ]
                    }, 
                    "type": 3, 
                    "uid": "511b2689-2401-4618-b607-d6587e7efd4c"
                }, 
                {
                    "adapter_option": [
                        false, 
                        false, 
                        false, 
                        false, 
                        71.0, 
                        5.0, 
                        83.0, 
                        -7.0
                    ], 
                    "children": [], 
                    "comp_anims": [], 
                    "event_list": [], 
                    "font": {
                        "__tuple__": true, 
                        "items": [
                            "", 
                            24
                        ]
                    }, 
                    "name": "label_25", 
                    "pos": {
                        "__tuple__": true, 
                        "items": [
                            95.0, 
                            17.0
                        ]
                    }, 
                    "pos_percent": {
                        "__tuple__": true, 
                        "items": [
                            95.0, 
                            17.0
                        ]
                    }, 
                    "size": {
                        "__tuple__": true, 
                        "items": [
                            24.0, 
                            24.0
                        ]
                    }, 
                    "text": {
                        "__tuple__": true, 
                        "items": [
                            "5", 
                            false
                        ]
                    }, 
                    "type": 3, 
                    "uid": "55f2376c-f0eb-4ce4-a17b-1adabb06f8f8"
                }, 
                {
                    "adapter_option": [
                        false, 
                        false, 
                        false, 
                        false, 
                        -55.0, 
                        97.0, 
                        19.0, 
                        23.0
                    ], 
                    "children": [], 
                    "comp_anims": [], 
                    "disabled_picture": null, 
                    "event_list": [], 
                    "name": "button_5", 
                    "normal_picture": 100350, 
                    "normal_text": {
                        "__tuple__": true, 
                        "items": [
                            " ", 
                            false
                        ]
                    }, 
                    "pos": {
                        "__tuple__": true, 
                        "items": [
                            50.0, 
                            148.0
                        ]
                    }, 
                    "pos_percent": {
                        "__tuple__": true, 
                        "items": [
                            50.0, 
                            148.0
                        ]
                    }, 
                    "press_picture": 100351, 
                    "size": {
                        "__tuple__": true, 
                        "items": [
                            58.0, 
                            58.0
                        ]
                    }, 
                    "suspend_picture": 100350, 
                    "type": 1, 
                    "uid": "27ba5b9e-a64c-40ce-b6c7-926eff9fc2cc"
                }, 
                {
                    "adapter_option": [
                        false, 
                        false, 
                        false, 
                        false, 
                        71.0, 
                        5.0, 
                        4.0, 
                        72.0
                    ], 
                    "children": [], 
                    "comp_anims": [], 
                    "event_list": [], 
                    "font": {
                        "__tuple__": true, 
                        "items": [
                            "", 
                            24
                        ]
                    }, 
                    "name": "label_26", 
                    "pos": {
                        "__tuple__": true, 
                        "items": [
                            16.0, 
                            17.0
                        ]
                    }, 
                    "pos_percent": {
                        "__tuple__": true, 
                        "items": [
                            16.0, 
                            17.0
                        ]
                    }, 
                    "size": {
                        "__tuple__": true, 
                        "items": [
                            24.0, 
                            24.0
                        ]
                    }, 
                    "text": {
                        "__tuple__": true, 
                        "items": [
                            "Q", 
                            false
                        ]
                    }, 
                    "type": 3, 
                    "uid": "7ae62f55-73c8-4937-b478-fc8351810a5a"
                }, 
                {
                    "adapter_option": [
                        false, 
                        false, 
                        false, 
                        false, 
                        0.0, 
                        0.0, 
                        1.0, 
                        -1.0
                    ], 
                    "children": [], 
                    "comp_anims": [], 
                    "event_list": [], 
                    "image": 101236, 
                    "name": "image_26", 
                    "opacity": 0.8, 
                    "open_adapter": true, 
                    "pos": {
                        "__tuple__": true, 
                        "items": [
                            51.0, 
                            50.0
                        ]
                    }, 
                    "pos_percent": {
                        "__tuple__": true, 
                        "items": [
                            51.0, 
                            50.0
                        ]
                    }, 
                    "size": {
                        "__tuple__": true, 
                        "items": [
                            100.0, 
                            100.0
                        ]
                    }, 
                    "type": 4, 
                    "uid": "0b6e059d-341c-43b8-aa6b-d9d5039d45e3"
                }, 
                {
                    "adapter_option": [
                        false, 
                        false, 
                        false, 
                        false, 
                        0.0, 
                        0.0, 
                        1.0, 
                        -1.0
                    ], 
                    "children": [], 
                    "comp_anims": [], 
                    "event_list": [], 
                    "image": 100387, 
                    "name": "image_27", 
                    "opacity": 0.8, 
                    "open_adapter": true, 
                    "pos": {
                        "__tuple__": true, 
                        "items": [
                            51.0, 
                            50.0
                        ]
                    }, 
                    "pos_percent": {
                        "__tuple__": true, 
                        "items": [
                            51.0, 
                            50.0
                        ]
                    }, 
                    "size": {
                        "__tuple__": true, 
                        "items": [
                            100.0, 
                            100.0
                        ]
                    }, 
                    "type": 4, 
                    "uid": "df9fcc8c-fb1b-431c-bbc8-dbfa2e7a53a4"
                }
            ], 
            "comp_anims": [], 
            "event_list": [], 
            "name": "skill_btn_1", 
            "pos": {
                "__tuple__": true, 
                "items": [
                    419.1641845703125, 
                    146.41790771484375
                ]
            }, 
            "pos_percent": {
                "__tuple__": true, 
                "items": [
                    21.83146794637044, 
                    13.557213677300348
                ]
            }, 
            "skill_cd_label": "d3dabf1e-db2c-46d1-b1e4-819d3a2f2500", 
            "skill_cd_progress": "9237ae2c-c137-47c7-b559-47aab4954152", 
            "skill_consume_mask_img": "0b6e059d-341c-43b8-aa6b-d9d5039d45e3", 
            "skill_disable_img": "df9fcc8c-fb1b-431c-bbc8-dbfa2e7a53a4", 
            "skill_frame_img": "b757181e-196a-4894-a2cc-a81cb9c899b2", 
            "skill_icon_img": "6cf27b84-f6eb-4991-8cc8-a3b0dfc56b54", 
            "skill_level_label": "511b2689-2401-4618-b607-d6587e7efd4c", 
            "skill_shortcut_label": "7ae62f55-73c8-4937-b478-fc8351810a5a", 
            "skill_stack_label": "55f2376c-f0eb-4ce4-a17b-1adabb06f8f8", 
            "skill_type": 3, 
            "skill_upgrade_btn": "27ba5b9e-a64c-40ce-b6c7-926eff9fc2cc", 
            "slot_id": 1, 
            "swallow_touches": true, 
            "type": 17, 
            "uid": "bba5195f-a063-48df-bf2d-617505356f33"
        }
    ], 
    "editor_visible": true, 
    "name": "PlayerState", 
    "opacity": 1.0, 
    "type": 2, 
    "uid": "54be3fda-7f1b-4554-83c0-644376540a59", 
    "visible": true, 
    "zorder": 400
}